prismtracker/__init__.py
prismtracker/aprs.py
prismtracker/beacon_algorithm.py
prismtracker/broadcast.py
prismtracker/gps.py
prismtracker/tracker.py
prismtracker-1.1.0.dist-info/LICENSE
prismtracker-1.1.0.dist-info/METADATA
prismtracker-1.1.0.dist-info/WHEEL
prismtracker-1.1.0.dist-info/entry_points.txt
prismtracker-1.1.0.dist-info/top_level.txt
prismtracker-1.1.0.dist-info/RECORD
