Metadata-Version: 2.1
Name: prismtracker
Version: 1.1.0
Summary: An APRS tracker daemon
Home-page: https://k6fsm.net/prismtracker
Author: Philip J Freeman
Author-email: elektron@halo.nu
License: UNKNOWN
Platform: UNKNOWN
Classifier: Programming Language :: Python :: 3
Classifier: License :: OSI Approved :: GNU General Public License v3 or later (GPLv3+)
Classifier: Operating System :: POSIX :: Linux
Requires-Python: >=3.6
License-File: LICENSE
Requires-Dist: aprslib (>=0.6.47)
Requires-Dist: gpsd-py3 (>=0.3.0)
Requires-Dist: gpxpy (>=1.4.2)
